pyproject.toml
setup.cfg
setup.py
src/ntl/__init__.py
src/ntl/__version__.py
src/ntl/ntl_helpers.cpp
src/ntl.egg-info/PKG-INFO
src/ntl.egg-info/SOURCES.txt
src/ntl.egg-info/dependency_links.txt
src/ntl.egg-info/requires.txt
src/ntl.egg-info/top_level.txt