Metadata-Version: 2.1
Name: ntl
Version: 0.0.0.dev1
Summary: Experimental bindings to NTL, a C++ library for doing Number Theory.
Home-page: UNKNOWN
License: UNKNOWN
Platform: UNKNOWN
Classifier: Development Status :: 2 - Pre-Alpha
Classifier: Programming Language :: Python
Classifier: Programming Language :: Python :: 3
Classifier: Programming Language :: Python :: 3.7
Classifier: Programming Language :: Python :: Implementation :: CPython
Requires-Python: >=3.7.0
Provides-Extra: tests
Provides-Extra: dev
Provides-Extra: docs
